{
  "scenario": "C3000_k10_T100_F1",
  "timestamp": "2026-03-06T21:19:12.741768",
  "config": {
    "seed": 123,
    "env": {
      "C": 3000.0,
      "k": 10,
      "T": 100,
      "F": 1,
      "enable_shaping": true
    },
    "train": {
      "episodes": 20,
      "max_steps": 1000,
      "batch_size": 256,
      "target_update_every": 20,
      "device": "cpu"
    },
    "eval": {
      "num_episodes": 100,
      "max_steps": 1000,
      "test_start_idx": 4000
    },
    "output": {
      "save_results": true
    },
    "plot": {
      "window": 100
    }
  },
  "paths": {
    "scenario": "C3000_k10_T100_F1",
    "data_dir": "data",
    "results_dir": "results/C3000_k10_T100_F1",
    "checkpoints_dir": "checkpoints/C3000_k10_T100_F1",
    "tx_pool_path": "data/tx_pool_T100.npy",
    "results_json_path": "results/C3000_k10_T100_F1/dqn_results.json",
    "eval_plot_path": "results/C3000_k10_T100_F1/dqn_evaluation.png",
    "training_plot_path": "results/C3000_k10_T100_F1/training_curves.png",
    "comparison_plot_path": "results/C3000_k10_T100_F1/dqn_vs_baseline.png",
    "config_snapshot_path": "results/C3000_k10_T100_F1/run_config.json",
    "model_path": "checkpoints/C3000_k10_T100_F1/k_wallet_dqn_aligned.pth",
    "baseline_results_path": "results/C3000_k10_T100_F1/baseline_results.json"
  }
}